SolidProp/PropertySI.py
SolidProp/__init__.py
SolidProp/add.py
SolidProp/PropData/ALUMINUM.json
SolidProp/PropData/COPPER.json
SolidProp/PropData/STAINLESSSTEEL316.json
pyHeatTransfer/__init__.py
pyHeatTransfer/conduction.py
pyHeatTransfer/convection.py
pyHeatTransfer/examples.py
pyHeatTransfer/geometry.py
pyHeatTransfer/heat.kv
pyHeatTransfer/interface.py
pyHeatTransfer/tests/__init__.py
pyHeatTransfer-0.1.11.dist-info/DESCRIPTION.rst
pyHeatTransfer-0.1.11.dist-info/METADATA
pyHeatTransfer-0.1.11.dist-info/RECORD
pyHeatTransfer-0.1.11.dist-info/WHEEL
pyHeatTransfer-0.1.11.dist-info/entry_points.txt
pyHeatTransfer-0.1.11.dist-info/metadata.json
pyHeatTransfer-0.1.11.dist-info/top_level.txt
